[
  {
    "slug": "scrummaster",
    "title": "Van vliegtuigsleper tot Scrum Master",
    "date": "2025-08-10",
    "excerpt": "Hoe ik van KLM pushback naar Scrum ging…",
    "cover": "/journal/klm-pushback-800w.avif",
    "words": 620
  },
  {
    "slug": "designchaos",
    "title": "Chaos ordenen met code en design",
    "date": "2025-09-01",
    "excerpt": "Waarom structuur niet saai is maar vrijheid geeft.",
    "cover":  "/journal/Design-Chaos-800w.avif",
    "words": 480
  },
  {
    "slug": "storytelling",
    "title": "Storytelling in IT",
    "date": "2025-09-05",
    "excerpt": "Waarom verhalen onmisbaar zijn in technologie.",
    "cover":  "/journal/klm-pushback-800w.avif",
    "words": 530
  },
  {
    "slug": "visual-branding",
    "title": "Visuele branding met karakter",
    "date": "2025-09-10",
    "excerpt": "Kleur, typografie en code: de kracht van design.",
    "cover":  "/journal/klm-pushback-800w.avif",
    "words": 600
  },
  {
    "slug": "team-energy",
    "title": "De energie van een team",
    "date": "2025-09-12",
    "excerpt": "Samenwerken, scherp blijven en elkaar optillen.",
    "cover":  "/journal/klm-pushback-800w.avif",
    "words": 400
  },
  {
    "slug": "toekomsttech",
    "title": "De toekomst van tech",
    "date": "2025-09-18",
    "excerpt": "AI, remote werken en de rol van creativiteit.",
    "cover":  "/journal/Typemachine-Toekomst-800w.avif",
    "words": 700
  }
]